madcubapy/__init__.py
madcubapy/coordinates/__init__.py
madcubapy/coordinates/conversions.py
madcubapy/coordinates/offsets.py
madcubapy/coordinates/spectral_data.py
madcubapy/coordinates/tests/__init__.py
madcubapy/coordinates/tests/test_conversions.py
madcubapy/coordinates/tests/test_offsets.py
madcubapy/coordinates/tests/test_spectral_data.py
madcubapy/coordinates/tests/test_transforms.py
madcubapy/coordinates/transforms.py
madcubapy/io/__init__.py
madcubapy/io/madcubafits.py
madcubapy/io/madcubamap.py
madcubapy/io/slim.py
madcubapy/io/spectracontainer.py
madcubapy/io/tests/__init__.py
madcubapy/io/tests/test_madcubafits.py
madcubapy/io/tests/test_madcubamap.py
madcubapy/io/tests/test_slim.py
madcubapy/io/tests/test_spectracontainer.py
madcubapy/operations/__init__.py
madcubapy/operations/maps/__init__.py
madcubapy/operations/maps/arithmetic.py
madcubapy/operations/maps/noise.py
madcubapy/operations/maps/tests/__init__.py
madcubapy/operations/maps/tests/test_arithmetic.py
madcubapy/operations/maps/tests/test_noise.py
madcubapy/regions/__init__.py
madcubapy/regions/carta.py
madcubapy/regions/contours.py
madcubapy/regions/ds9.py
madcubapy/regions/interface.py
madcubapy/regions/madcuba.py
madcubapy/regions/patches.py
madcubapy/regions/pyroi.py
madcubapy/regions/tests/__init__.py
madcubapy/regions/tests/test_parsers.py
madcubapy/utils/__init__.py
madcubapy/utils/geometry.py
madcubapy/utils/numeric.py
madcubapy/utils/spectral.py
madcubapy/utils/tests/__init__.py
madcubapy/utils/tests/test_numeric.py
madcubapy/utils/tests/test_spectral.py
madcubapy/visualization/__init__.py
madcubapy/visualization/interaction.py
madcubapy/visualization/quick_plotters.py
madcubapy/visualization/tests/__init__.py
madcubapy/visualization/tests/test_interaction.py
madcubapy/visualization/tests/test_quick_plotters.py
madcubapy/visualization/tests/test_wcsaxes_helpers.py
madcubapy/visualization/tests/test_zoom_syncers.py
madcubapy/visualization/wcsaxes_helpers.py
madcubapy-0.8.3.dist-info/LICENSE
madcubapy-0.8.3.dist-info/METADATA
madcubapy-0.8.3.dist-info/WHEEL
madcubapy-0.8.3.dist-info/RECORD
