Metadata-Version: 2.3
Name: madcubapy
Version: 0.8.3
Summary: The MADCUBA python package.
License: MIT License
Keywords: madcuba,radio astronomy
Author: David Haasler García
Author-email: dhaasler@cab.inta-csic.es
Requires-Python: >=3.9
Classifier: Development Status :: 2 - Pre-Alpha
Classifier: License :: OSI Approved :: MIT License
Classifier: Intended Audience :: Science/Research
Classifier: Programming Language :: Python :: 3
Classifier: Operating System :: OS Independent
Provides-Extra: docs
Requires-Dist: astropy (>=6.0.0)
Requires-Dist: astropy[recommended] ; extra == "docs"
Requires-Dist: ipython
Requires-Dist: matplotlib (>=3.6.0)
Requires-Dist: matplotlib ; extra == "docs"
Requires-Dist: numpy (>=1.23.2)
Requires-Dist: numpydoc ; extra == "docs"
Requires-Dist: pydata_sphinx_theme ; extra == "docs"
Requires-Dist: scipy (>=1.9.2)
Requires-Dist: sphinx ; extra == "docs"
Requires-Dist: sphinx-automodapi ; extra == "docs"
Requires-Dist: sphinx-design ; extra == "docs"
Requires-Dist: sphinx_changelog ; extra == "docs"
Requires-Dist: sphinx_gallery ; extra == "docs"
Project-URL: Documentation, https://madcubapy.readthedocs.io/
Project-URL: Homepage, https://github.com/dhaasler/madcubapy
Project-URL: Repository, https://github.com/dhaasler/madcubapy.git
Project-URL: changelog, https://github.com/dhaasler/madcubapy/blob/main/CHANGELOG.rst
